vc_toolkit/__init__.py
vc_toolkit/conversion/__init__.py
vc_toolkit/conversion/converter.py
vc_toolkit/conversion/converter_trainer.py
vc_toolkit/conversion/mixer.py
vc_toolkit/img/icon.png
vc_toolkit/img/loading.gif
vc_toolkit/main.py
vc_toolkit/models/manifest.yml
vc_toolkit/presenter/__init__.py
vc_toolkit/presenter/common.py
vc_toolkit/presenter/conversion.py
vc_toolkit/presenter/mixing.py
vc_toolkit/presenter/separation.py
vc_toolkit/presenter/training.py
vc_toolkit/separation/__init__.py
vc_toolkit/separation/audio.py
vc_toolkit/separation/constants.py
vc_toolkit/separation/data.py
vc_toolkit/separation/evaluator.py
vc_toolkit/separation/logger.py
vc_toolkit/separation/models.py
vc_toolkit/separation/preprocess.py
vc_toolkit/separation/separator.py
vc_toolkit/separation/utility.py
vc_toolkit/separation_evaluation.py
vc_toolkit/separation_preprocess.py
vc_toolkit/separation_train.py
vc_toolkit/utility/__init__.py
vc_toolkit/utility/functions.py
vc_toolkit/widget/__init__.py
vc_toolkit/widget/common.py
vc_toolkit/widget/conversion.py
vc_toolkit/widget/loading_overlay.py
vc_toolkit/widget/loading_window.py
vc_toolkit/widget/main_window.py
vc_toolkit/widget/mixing.py
vc_toolkit/widget/separation.py
vc_toolkit/widget/training.py
voice_conversion_toolkit-1.0.0.dist-info/METADATA
voice_conversion_toolkit-1.0.0.dist-info/WHEEL
voice_conversion_toolkit-1.0.0.dist-info/entry_points.txt
voice_conversion_toolkit-1.0.0.dist-info/RECORD
